faunanet/__init__.py
faunanet/default.yml
faunanet/docker-compose.yml
faunanet/faunanet.dockerfile
faunanet/faunanet_arm.dockerfile
faunanet/faunanet_setup.py
faunanet/install.yml
faunanet/model_base.py
faunanet/preprocessor_base.py
faunanet/recording.py
faunanet/repl.py
faunanet/species_predictor.py
faunanet/startup_docker.py
faunanet/utils.py
faunanet/watcher.py
faunanet-0.0.12.dist-info/LICENSE
faunanet-0.0.12.dist-info/METADATA
faunanet-0.0.12.dist-info/WHEEL
faunanet-0.0.12.dist-info/entry_points.txt
faunanet-0.0.12.dist-info/top_level.txt
faunanet-0.0.12.dist-info/RECORD
