Metadata-Version: 2.1
Name: faunanet
Version: 0.0.12
Summary: faunanet - A bioacoustics platform for the analysis of animal sounds with neural networks based on birdnetlib
Author-email: Harald Mack <harald.mack@uni-heidelberg.de>, Inga Ulusoy <inga.ulusoy@uni-heidelberg.de>
License: Apache License
Project-URL: Repository, https://github.com/ssciwr/iSparrow
Project-URL: Issues, https://github.com/ssciwr/iSparrow/issues
Project-URL: Documentation, https://isparrow.readthedocs.io/en/latest/
Classifier: Programming Language :: Python :: 3.9
Classifier: Operating System :: OS Independent
Classifier: License :: OSI Approved :: Apache Software License
Classifier: Development Status :: 4 - Beta
Classifier: Topic :: Multimedia :: Sound/Audio :: Analysis
Classifier: Topic :: Scientific/Engineering :: Artificial Intelligence
Requires-Python: >=3.9
License-File: LICENSE
Requires-Dist: librosa
Requires-Dist: PyYAML
Requires-Dist: birdnetlib ==0.15.0
Requires-Dist: pooch
Requires-Dist: resampy
Requires-Dist: platformdirs
Requires-Dist: ffmpeg-python
Provides-Extra: dev
Requires-Dist: pytest ; extra == 'dev'
Requires-Dist: pytest-cov ; extra == 'dev'
Requires-Dist: coverage ; extra == 'dev'
Requires-Dist: pre-commit ; extra == 'dev'
Requires-Dist: pytest-mock ; extra == 'dev'
Requires-Dist: pandas ; extra == 'dev'
Provides-Extra: doc
Requires-Dist: sphinx ; extra == 'doc'
Requires-Dist: myst-parser ; extra == 'doc'
Requires-Dist: sphinxcontrib-napoleon ; extra == 'doc'
Requires-Dist: sphinx-rtd-theme ; extra == 'doc'
Provides-Extra: tensorflow
Requires-Dist: numpy ; extra == 'tensorflow'
Requires-Dist: tensorflow ; extra == 'tensorflow'
Provides-Extra: tensorflow-arm
Requires-Dist: numpy <2.0 ; extra == 'tensorflow-arm'
Requires-Dist: tensorflow-aarch64 ; extra == 'tensorflow-arm'
Provides-Extra: tensorflow-lite
Requires-Dist: numpy <2.0 ; extra == 'tensorflow-lite'
Requires-Dist: tflite-runtime ; extra == 'tensorflow-lite'
